ap_health_report/__init__.py
ap_health_report/report.py
ap_health_report-0.1.2.dist-info/licenses/LICENSE
ap_health_report-0.1.2.dist-info/METADATA
ap_health_report-0.1.2.dist-info/WHEEL
ap_health_report-0.1.2.dist-info/top_level.txt
ap_health_report-0.1.2.dist-info/RECORD
