Metadata-Version: 2.4
Name: ap_health_report
Version: 0.1.2
Summary: WiFi AP log analysis and health reporting
Author: AirowireAILabs
Author-email: AirowireAILabs <ailabs@airowire.com>
License: MIT License
Requires-Python: >=3.7
License-File: LICENSE
Requires-Dist: pandas>=1.0.0
Requires-Dist: numpy>=1.18.0
Dynamic: license-file
